gdsii/__init__.py
gdsii/_records.py
gdsii/elements.py
gdsii/exceptions.py
gdsii/library.py
gdsii/record.py
gdsii/structure.py
gdsii/tags.py
gdsii/types.py
gdsii/scripts/__init__.py
gdsii/scripts/gds2txt.py
gdsii/scripts/gds2yaml.py
gdsii/scripts/txt2gds.py
python_gdsii-0.2.3.dist-info/licenses/LGPL-3
python_gdsii-0.2.3.dist-info/METADATA
python_gdsii-0.2.3.dist-info/WHEEL
python_gdsii-0.2.3.dist-info/entry_points.txt
python_gdsii-0.2.3.dist-info/top_level.txt
python_gdsii-0.2.3.dist-info/RECORD
