Metadata-Version: 2.4
Name: python-gdsii
Version: 0.2.3
Summary: GDSII manipulation library
Author-email: Ievgenii Meshcheriakov <eugen@debian.org>
License-Expression: LGPL-3.0-or-later
Project-URL: Documentation, https://python-gdsii.readthedocs.io/en/latest/
Project-URL: Repository, https://github.com/eugmes/python-gdsii.git
Project-URL: Issues, https://github.com/eugmes/python-gdsii/issues
Classifier: Development Status :: 3 - Alpha
Classifier: Environment :: Console
Classifier: Intended Audience :: Developers
Classifier: Programming Language :: Python
Classifier: Topic :: Scientific/Engineering :: Electronic Design Automation (EDA)
Classifier: Topic :: Software Development :: Libraries :: Python Modules
License-File: LGPL-3
Provides-Extra: yaml
Requires-Dist: pyyaml; extra == "yaml"
Dynamic: license-file
